<?xml version="1.0"?>
<block>
  <name>aausat_parser</name>
  <key>aausat_aausat_parser</key>
  <category>aausat</category>
  <import>import aausat</import>
  <make>aausat.aausat_parser()</make>
  <!-- Make one 'param' node for every Parameter you want settable from the GUI.
       Sub-nodes:
       * name
       * key (makes the value accessible as $keyname, e.g. in the make node)
       * type -->

  <!-- Make one 'sink' node per input. Sub-nodes:
       * name (an identifier for the GUI)
       * type
       * vlen
       * optional (set to 1 for optional inputs) -->
  <sink>
    <name>in</name>
    <type>byte</type>
  </sink>
</block>
